ShenduXuexiLilunYuShizhanTigaoPian/README.md
ShenduXuexiLilunYuShizhanTigaoPian/__init__.py
ShenduXuexiLilunYuShizhanTigaoPian/__main__.py
ShenduXuexiLilunYuShizhanTigaoPian/file.epub
ShenduXuexiLilunYuShizhanTigaoPian/index.html
ShenduXuexiLilunYuShizhanTigaoPian/css/__init__.py
ShenduXuexiLilunYuShizhanTigaoPian/css/annotations.css
ShenduXuexiLilunYuShizhanTigaoPian/css/main.css
ShenduXuexiLilunYuShizhanTigaoPian/css/normalize.css
ShenduXuexiLilunYuShizhanTigaoPian/css/popup.css
ShenduXuexiLilunYuShizhanTigaoPian/font/__init__.py
ShenduXuexiLilunYuShizhanTigaoPian/font/fontello.eot
ShenduXuexiLilunYuShizhanTigaoPian/font/fontello.svg
ShenduXuexiLilunYuShizhanTigaoPian/font/fontello.ttf
ShenduXuexiLilunYuShizhanTigaoPian/font/fontello.woff
ShenduXuexiLilunYuShizhanTigaoPian/img/__init__.py
ShenduXuexiLilunYuShizhanTigaoPian/img/annotator-glyph-sprite.png
ShenduXuexiLilunYuShizhanTigaoPian/img/annotator-icon-sprite.png
ShenduXuexiLilunYuShizhanTigaoPian/img/apple-touch-icon.png
ShenduXuexiLilunYuShizhanTigaoPian/img/cancelfullscreen.png
ShenduXuexiLilunYuShizhanTigaoPian/img/close.png
ShenduXuexiLilunYuShizhanTigaoPian/img/fullscreen.png
ShenduXuexiLilunYuShizhanTigaoPian/img/loader.gif
ShenduXuexiLilunYuShizhanTigaoPian/img/menu-icon.png
ShenduXuexiLilunYuShizhanTigaoPian/img/save.png
ShenduXuexiLilunYuShizhanTigaoPian/img/saved.png
ShenduXuexiLilunYuShizhanTigaoPian/img/settings-s.png
ShenduXuexiLilunYuShizhanTigaoPian/img/settings.png
ShenduXuexiLilunYuShizhanTigaoPian/img/star.png
ShenduXuexiLilunYuShizhanTigaoPian/js/__init__.py
ShenduXuexiLilunYuShizhanTigaoPian/js/epub.js
ShenduXuexiLilunYuShizhanTigaoPian/js/epub.min.js
ShenduXuexiLilunYuShizhanTigaoPian/js/epub.min.map
ShenduXuexiLilunYuShizhanTigaoPian/js/hooks.min.js
ShenduXuexiLilunYuShizhanTigaoPian/js/hooks.min.map
ShenduXuexiLilunYuShizhanTigaoPian/js/reader.js
ShenduXuexiLilunYuShizhanTigaoPian/js/reader.js.map
ShenduXuexiLilunYuShizhanTigaoPian/js/reader.min.js
shendu_xuexi_lilun_yu_shizhan_tigao_pian-2024.3.5.0.dist-info/METADATA
shendu_xuexi_lilun_yu_shizhan_tigao_pian-2024.3.5.0.dist-info/WHEEL
shendu_xuexi_lilun_yu_shizhan_tigao_pian-2024.3.5.0.dist-info/entry_points.txt
shendu_xuexi_lilun_yu_shizhan_tigao_pian-2024.3.5.0.dist-info/top_level.txt
shendu_xuexi_lilun_yu_shizhan_tigao_pian-2024.3.5.0.dist-info/RECORD
